pygal_maps_es/__init__.py
pygal_maps_es/es.departments.svg
pygal_maps_es/es.regions.svg
pygal_maps_es/maps.py
pygal_maps_es/test/__init__.py
pygal_maps_es/test/test_maps.py
pygal_maps_es-1.1.0.dist-info/DESCRIPTION.rst
pygal_maps_es-1.1.0.dist-info/METADATA
pygal_maps_es-1.1.0.dist-info/RECORD
pygal_maps_es-1.1.0.dist-info/WHEEL
pygal_maps_es-1.1.0.dist-info/entry_points.txt
pygal_maps_es-1.1.0.dist-info/metadata.json
pygal_maps_es-1.1.0.dist-info/top_level.txt
