Metadata-Version: 1.1
Name: pygal-maps-es
Version: 1.1.0
Summary: Spanish maps for pygal
Home-page: http://github.com/Markcial/pygal_maps_es
Author: Marc Garcia Sastre
Author-email: markcial@gmail.com
License: GNU LGPL v3+
Keywords: svg,chart,graph,maps,spanish
Platform: Any
Classifier: Development Status :: 4 - Beta
Classifier: Environment :: Console
Classifier: Intended Audience :: End Users/Desktop
Classifier: License :: OSI Approved :: GNU Lesser General Public License v3 or later (LGPLv3+)
Classifier: Operating System :: OS Independent
Classifier: Programming Language :: Python :: 2
Classifier: Programming Language :: Python :: 3
Classifier: Topic :: Multimedia :: Graphics :: Presentation
Provides: pygal_maps_es
